[
  {
    "id": "pelicula_001",
    "titulo": "Dune: Parte Dos",
    "sinopsis": "Paul Atreides se une a los Fremen y comienza un viaje espiritual y marcial para convertirse en Muad'dib...",
    "elenco": ["Timothée Chalamet", "Zendaya", "Rebecca Ferguson"],
    "anio": 2024,
    "genero": ["Ciencia Ficción", "Aventura", "Drama"],
    "calificacion": 8.9,
    "poster": "https://es.web.img3.acsta.net/pictures/24/02/20/17/42/2385575.jpg",
    "iframes": [
      "https://sedrfmwrpjxatem5.premilkyway.com/hls2/01/02053/6dz22bl4exq4_,n,h,.urlset/index-f1-v1-a1.m3u8?t=DuG6dJqRxXYw1kyBsWQSgrqI1Feo8z23hC478MfQsyU&s=1747972243&e=129600&f=10266099&srv=js4BwLKgfmTMJmVh&i=0.4&sp=500&p1=js4BwLKgfmTMJmVh&p2=js4BwLKgfmTMJmVh&asn=28118"
    ]
  },
  {
    "id": "pelicula_002",
    "titulo": "Oppenheimer",
    "sinopsis": "La historia del científico J. Robert Oppenheimer y su papel en el desarrollo de la bomba atomica.",
    "elenco": ["Cillian Murphy", "Emily Blunt", "Matt Damon"],
    "anio": 2023,
    "genero": ["Biografía", "Drama", "Historia"],
    "calificacion": 8.6,
    "poster": "https://image.tmdb.org/t/p/w500/8Gxv8gSFCU0XGDykEGv7zR1n2ua.jpg",
    "iframes": [
      "https://62lcxnbxr456.premilkyway.com/hls2/01/10374/h54yq08aiqyn_,l,n,.urlset/index-f2-v1-a1.m3u8?t=jOJ2w_bOgNi9B-kaluf-laollRnwFb8GyWpQeScpqM0&s=1747972335&e=129600&f=51870185&srv=ts09ruf2imyzcv&i=0.4&sp=500&p1=ts09ruf2imyzcv&p2=ts09ruf2imyzcv&asn=28118"  
    ]
  }
]
